LICENSE
README.md
swing_hello/__init__.py
swing_hello/__main__.py
swing_hello/apps.py
swing_hello/forms/__init__.py
swing_hello/forms/form_hello.py
swing_hello/locale/.gitkeep
swing_hello/migrations/__init__.py
swing_hello/templates/swing_hello/hello_form.html
swing_hello/templates/swing_hello/hello_template.html
swing_hello/tests/__init__.py
swing_hello/tests/test_view_hello_form.py
swing_hello/tests/test_view_hello_json.py
swing_hello/tests/test_view_hello_response.py
swing_hello/tests/test_view_hello_template.py
swing_hello/urls.py
swing_hello/views/__init__.py
swing_hello/views/view_hello_form.py
swing_hello/views/view_hello_json.py
swing_hello/views/view_hello_response.py
swing_hello/views/view_hello_template.py
swing_hello-0.1.3.dist-info/AUTHORS
swing_hello-0.1.3.dist-info/LICENSE
swing_hello-0.1.3.dist-info/METADATA
swing_hello-0.1.3.dist-info/NOTICE
swing_hello-0.1.3.dist-info/WHEEL
swing_hello-0.1.3.dist-info/entry_points.txt
swing_hello-0.1.3.dist-info/RECORD
