Metadata-Version: 2.1
Name: swing_hello
Version: 0.1.3
Summary: A Django plugin that provides basic views for response handling and template rendering.
Home-page: https://github.com/scape-agency/swing-hello
License: MIT
Keywords: Django,plugin,views,template,response-handling
Author: Scape Agency
Author-email: info@scapeagency.com
Requires-Python: >=3.10,<4.0
Classifier: Development Status :: 3 - Alpha
Classifier: Framework :: Django
Classifier: Intended Audience :: Developers
Classifier: License :: OSI Approved :: MIT License
Classifier: Programming Language :: Python :: 3
Classifier: Programming Language :: Python :: 3.10
Classifier: Programming Language :: Python :: 3.11
Classifier: Programming Language :: Python :: 3.12
Classifier: Programming Language :: Python :: 3.13
Classifier: Topic :: Software Development :: Libraries :: Python Modules
Requires-Dist: Django (>=5.1,<6.0)
Project-URL: Documentation, https://swing-hello.readthedocs.io
Project-URL: Repository, https://github.com/scape-agency/swing-hello
